{"cameraMode":{"drawMode":0,"name":"Shaded","section":"Shading Mode"},"sceneLighting":false,"audioPlay":false,"sceneViewState":{"m_AlwaysRefresh":false,"showFog":true,"showSkybox":false,"showFlares":true,"showImageEffects":true,"showParticleSystems":true,"showVisualEffectGraphs":true,"m_FxEnabled":true},"in2DMode":false,"pivot":{"x":76.96925354003906,"y":1.9294449090957642,"z":119.00511932373047},"rotation":{"x":0.2869183123111725,"y":-0.5536946654319763,"z":0.21113049983978272,"w":0.7526978850364685},"size":0.7552421689033508,"orthographic":false}